ecoguard_ai/__init__.py
ecoguard_ai/__main__.py
ecoguard_ai/analyzers/__init__.py
ecoguard_ai/analyzers/base.py
ecoguard_ai/analyzers/ai_code/__init__.py
ecoguard_ai/analyzers/green/__init__.py
ecoguard_ai/analyzers/quality/__init__.py
ecoguard_ai/analyzers/security/__init__.py
ecoguard_ai/cli/__init__.py
ecoguard_ai/core/__init__.py
ecoguard_ai/core/analyzer.py
ecoguard_ai/core/issue.py
ecoguard_ai/core/result.py
ecoguard_ai/research/__init__.py
ecoguard_ai/research/ast_analysis.py
ecoguard_ai/research/multi_language_parsers.py
ecoguard_ai-0.1.3.dist-info/licenses/LICENSE
ecoguard_ai-0.1.3.dist-info/METADATA
ecoguard_ai-0.1.3.dist-info/WHEEL
ecoguard_ai-0.1.3.dist-info/entry_points.txt
ecoguard_ai-0.1.3.dist-info/top_level.txt
ecoguard_ai-0.1.3.dist-info/RECORD
