Metadata-Version: 2.4
Name: ecoguard-ai
Version: 0.1.3
Summary: AI-augmented software development pipeline solution for quality, security, and environmental sustainability
Author-email: EcoGuard AI Team <team@ecoguard-ai.org>
License-Expression: MIT
Project-URL: Homepage, https://github.com/ecoguard-ai/ecoguard-ai
Project-URL: Documentation, https://docs.ecoguard-ai.org
Project-URL: Repository, https://github.com/ecoguard-ai/ecoguard-ai
Project-URL: Bug Tracker, https://github.com/ecoguard-ai/ecoguard-ai/issues
Classifier: Development Status :: 3 - Alpha
Classifier: Intended Audience :: Developers
Classifier: Programming Language :: Python :: 3.8
Classifier: Programming Language :: Python :: 3.9
Classifier: Programming Language :: Python :: 3.10
Classifier: Programming Language :: Python :: 3.11
Classifier: Programming Language :: Python :: 3.12
Classifier: Topic :: Software Development :: Quality Assurance
Classifier: Topic :: Security
Classifier: Topic :: Software Development :: Libraries :: Python Modules
Requires-Python: >=3.8
License-File: LICENSE
Requires-Dist: click>=8.0.0
Requires-Dist: pydantic>=2.0.0
Requires-Dist: rich>=13.0.0
Requires-Dist: PyYAML>=6.0
Requires-Dist: toml>=0.10.2
Requires-Dist: typing-extensions>=4.0.0
Provides-Extra: dev
Requires-Dist: black>=23.0.0; extra == "dev"
Requires-Dist: flake8>=6.0.0; extra == "dev"
Requires-Dist: flake8-docstrings>=1.7.0; extra == "dev"
Requires-Dist: flake8-type-checking>=2.7.0; extra == "dev"
Requires-Dist: flake8-bugbear>=23.12.0; extra == "dev"
Requires-Dist: mypy>=1.5.0; extra == "dev"
Requires-Dist: isort>=5.13.0; extra == "dev"
Requires-Dist: ruff>=0.1.14; extra == "dev"
Requires-Dist: pytest>=7.0.0; extra == "dev"
Requires-Dist: pytest-cov>=4.0.0; extra == "dev"
Requires-Dist: pytest-xdist>=3.5.0; extra == "dev"
Requires-Dist: pytest-mock>=3.12.0; extra == "dev"
Requires-Dist: pytest-benchmark>=4.0.0; extra == "dev"
Requires-Dist: coverage[toml]>=7.2.0; extra == "dev"
Requires-Dist: pre-commit>=3.5.0; extra == "dev"
Requires-Dist: tox>=4.11.0; extra == "dev"
Requires-Dist: twine>=4.0.0; extra == "dev"
Requires-Dist: wheel>=0.42.0; extra == "dev"
Requires-Dist: check-manifest>=0.49; extra == "dev"
Requires-Dist: sphinx>=7.2.0; extra == "dev"
Requires-Dist: sphinx-rtd-theme>=2.0.0; extra == "dev"
Requires-Dist: myst-parser>=2.0.0; extra == "dev"
Requires-Dist: pydocstyle>=6.3.0; extra == "dev"
Requires-Dist: ipdb>=0.13.0; extra == "dev"
Requires-Dist: line-profiler>=4.1.0; extra == "dev"
Provides-Extra: runtime
Requires-Dist: codecarbon>=2.3.0; extra == "runtime"
Requires-Dist: memory-profiler>=0.61.0; extra == "runtime"
Requires-Dist: psutil>=5.9.0; extra == "runtime"
Requires-Dist: py-cpuinfo>=9.0.0; extra == "runtime"
Provides-Extra: security
Requires-Dist: bandit[toml]>=1.7.5; extra == "security"
Requires-Dist: safety>=3.0.0; extra == "security"
Requires-Dist: semgrep>=1.45.0; extra == "security"
Requires-Dist: pip-audit>=2.6.0; extra == "security"
Requires-Dist: detect-secrets>=1.4.0; extra == "security"
Provides-Extra: server
Requires-Dist: fastapi>=0.108.0; extra == "server"
Requires-Dist: uvicorn[standard]>=0.25.0; extra == "server"
Requires-Dist: sqlalchemy>=2.0.25; extra == "server"
Requires-Dist: alembic>=1.13.0; extra == "server"
Requires-Dist: psycopg2-binary>=2.9.9; extra == "server"
Requires-Dist: redis>=5.0.0; extra == "server"
Requires-Dist: celery>=5.3.0; extra == "server"
Provides-Extra: ai
Requires-Dist: openai>=1.7.0; extra == "ai"
Requires-Dist: anthropic>=0.8.0; extra == "ai"
Requires-Dist: tiktoken>=0.5.0; extra == "ai"
Requires-Dist: sentence-transformers>=2.2.0; extra == "ai"
Dynamic: license-file
